eyja_email/__init__.py
eyja_email/models/__init__.py
eyja_email/models/email.py
eyja_email/operators/__init__.py
eyja_email/operators/email/__init__.py
eyja_email/operators/email/operator.py
eyja_email/operators/email/statuses.py
tests/__init__.py
tests/test_email.py
eyja_email-0.1.1.dist-info/METADATA
eyja_email-0.1.1.dist-info/WHEEL
eyja_email-0.1.1.dist-info/top_level.txt
eyja_email-0.1.1.dist-info/zip-safe
eyja_email-0.1.1.dist-info/RECORD
